qmpy_rester/__init__.py
qmpy_rester/rester.py
qmpy_rester-0.2.0.dist-info/LICENSE
qmpy_rester-0.2.0.dist-info/METADATA
qmpy_rester-0.2.0.dist-info/WHEEL
qmpy_rester-0.2.0.dist-info/top_level.txt
qmpy_rester-0.2.0.dist-info/RECORD
