Metadata-Version: 2.1
Name: qmpy-rester
Version: 0.2.0
Summary: A python wrapper for OQMD API
Home-page: https://github.com/mohanliu/qmpy_rester
Author: Mohan Liu
Author-email: mohan@u.northwestern.edu
License: LICENSE
Platform: UNKNOWN
Requires-Dist: requests
